<?xml version="1.0"?>
<view xmlns:xsi="http://www.w3.org/2001/XMLSchema-instance" xsi:noNamespaceSchemaLocation="urn:magento:framework:Config/etc/view.xsd">
    <media>
        <images module="Magento_Catalog">
            <image id="product_base_image" type="image">
                <width>700</width>
                <height>700</height>
            </image>
            <image id="product_small_image" type="small_image">
                <width>300</width>
                <height>300</height>
            </image>
            <image id="product_thumbnail_image" type="thumbnail">
                <width>100</width>
                <height>100</height>
            </image>
        </images>
    </media>
</view>
